[
  {
    "id": "intuitive-home",
    "title": "Intuitive | Maker of Da Vinci & Ion Robotic Systems",
    "url": "https://www.intuitive.com/",
    "kind": "product-page",
    "publisher": "Intuitive Surgical",
    "note": "Official company and product overview for da Vinci, Ion, and related services.",
    "accessedOn": "2026-05-25"
  },
  {
    "id": "intuitive-da-vinci-5",
    "title": "Meet the da Vinci 5 robotic surgical system",
    "url": "https://www.intuitive.com/en-us/products-and-services/da-vinci/5",
    "kind": "product-page",
    "publisher": "Intuitive Surgical",
    "note": "Official product page describing the current-generation da Vinci 5 platform.",
    "accessedOn": "2026-05-25"
  },
  {
    "id": "intuitive-da-vinci-instruments",
    "title": "Da Vinci Surgical Instruments",
    "url": "https://www.intuitive.com/en-us/products-and-services/da-vinci/instruments",
    "kind": "product-page",
    "publisher": "Intuitive Surgical",
    "note": "Official page documenting da Vinci instruments and third-party compatibility process context.",
    "accessedOn": "2026-05-25"
  },
  {
    "id": "intuitive-ion-page",
    "title": "Ion Robotic Bronchoscopy",
    "url": "https://www.intuitive.com/en-us/products-and-services/ion",
    "kind": "product-page",
    "publisher": "Intuitive Surgical",
    "note": "Official Ion product page for robotic-assisted bronchoscopy positioning.",
    "accessedOn": "2026-05-25"
  },
  {
    "id": "intuitive-ion-ai-release",
    "title": "Intuitive expands AI and advanced imaging integration in Ion Endoluminal System",
    "url": "https://isrg.intuitive.com/node/22361/pdf",
    "kind": "investor-relations",
    "publisher": "Intuitive Surgical",
    "note": "Company release describing Ion's shape-sensing catheter and advanced imaging integration direction.",
    "accessedOn": "2026-05-25"
  },
  {
    "id": "intuitive-2025-10k",
    "title": "Form 10-K for Intuitive Surgical Inc. filed 02/03/2026",
    "url": "https://isrg.gcs-web.com/static-files/f684d492-5169-48b5-9723-8ebcaa05c098",
    "kind": "annual-report",
    "publisher": "Intuitive Surgical",
    "note": "Primary annual filing for business model, risk factors, installed base, procedure growth, revenue, and profitability context.",
    "accessedOn": "2026-05-25"
  },
  {
    "id": "intuitive-2026-q1-10q",
    "title": "Form 10-Q for Intuitive Surgical Inc. filed 04/22/2026",
    "url": "https://investor.intuitivesurgical.com/static-files/8d536618-2150-41fb-b463-a6d6691d59bd",
    "kind": "regulatory-filing",
    "publisher": "Intuitive Surgical",
    "note": "Recent quarterly filing used as a 2026 financial and operating update.",
    "accessedOn": "2026-05-25"
  },
  {
    "id": "stockanalysis-isrg-market-cap",
    "title": "Intuitive Surgical Market Cap & Net Worth",
    "url": "https://stockanalysis.com/stocks/isrg/market-cap/",
    "kind": "market-data",
    "publisher": "StockAnalysis",
    "note": "Market capitalization snapshot and historical market-cap context.",
    "accessedOn": "2026-05-25"
  },
  {
    "id": "stockanalysis-isrg-statistics",
    "title": "Intuitive Surgical Statistics & Valuation",
    "url": "https://stockanalysis.com/stocks/isrg/statistics/",
    "kind": "market-data",
    "publisher": "StockAnalysis",
    "note": "Point-in-time valuation, trailing P/E, revenue, and profit metrics.",
    "accessedOn": "2026-05-25"
  },
  {
    "id": "stockanalysis-isrg-profile",
    "title": "Intuitive Surgical Company Profile",
    "url": "https://stockanalysis.com/stocks/isrg/company/",
    "kind": "market-data",
    "publisher": "StockAnalysis",
    "note": "Company profile and IPO date reference.",
    "accessedOn": "2026-05-25"
  },
  {
    "id": "stockanalysis-isrg-ratios",
    "title": "Intuitive Surgical Financial Ratios",
    "url": "https://stockanalysis.com/stocks/isrg/financials/ratios/",
    "kind": "market-data",
    "publisher": "StockAnalysis",
    "note": "Valuation ratio history and current ratio context.",
    "accessedOn": "2026-05-25"
  },
  {
    "id": "renaissance-isrg-ipo",
    "title": "Intuitive Surgical prices 5 million shares at $9",
    "url": "https://www.renaissancecapital.com/IPO-Center/News/2730/Intuitive-Surgical-prices-5-million-shares-at-%249%3B-ends-its-first-day-of-tra",
    "kind": "market-data",
    "publisher": "Renaissance Capital",
    "note": "IPO pricing and June 2000 offering context.",
    "accessedOn": "2026-05-25"
  },
  {
    "id": "raven-open-platform",
    "title": "Raven-II: An Open Platform for Surgical Robotics Research",
    "url": "https://ieeexplore.ieee.org/document/6363574",
    "kind": "analysis",
    "publisher": "IEEE",
    "note": "Canonical research reference for Raven II as an open surgical robotics platform.",
    "accessedOn": "2026-05-25"
  },
  {
    "id": "berkeley-raven",
    "title": "Raven: Open Surgical Robotic Platforms",
    "url": "https://rll.berkeley.edu/surgical/",
    "kind": "open-source-project",
    "publisher": "UC Berkeley Robot Learning Lab",
    "note": "Project page for open-architecture Raven surgical robotics research.",
    "accessedOn": "2026-05-25"
  },
  {
    "id": "ros-docs",
    "title": "About ROS",
    "url": "https://docs.ros.org/en/ros2_documentation/rolling/About-ROS.html",
    "kind": "technical-docs",
    "publisher": "Open Robotics",
    "note": "Official documentation describing ROS as an open-source robotics ecosystem.",
    "accessedOn": "2026-05-25"
  },
  {
    "id": "continuum-open-source",
    "title": "A Continuum Manipulator for Open-Source Surgical Robotics Research and Shared Development",
    "url": "https://arxiv.org/abs/2101.01080",
    "kind": "analysis",
    "publisher": "arXiv",
    "note": "Research source for open-source continuum manipulator development relevant to minimally invasive robotics.",
    "accessedOn": "2026-05-25"
  },
  {
    "id": "low-cost-open-surgical-robot",
    "title": "A Low-Cost Teleoperable Surgical Robot with a Macro-Micro Structure and a Continuum Tip for Open-Source Research",
    "url": "https://arxiv.org/abs/2405.16084",
    "kind": "analysis",
    "publisher": "arXiv",
    "note": "Research source documenting open-source designs, code, CAD, and bill-of-materials direction for lower-cost surgical robotics research.",
    "accessedOn": "2026-05-25"
  },
  {
    "id": "midas-surgical",
    "title": "MiDAS: A Multimodal Data Acquisition System and Dataset for Robot-Assisted Minimally Invasive Surgery",
    "url": "https://arxiv.org/abs/2602.12407",
    "kind": "analysis",
    "publisher": "arXiv",
    "note": "Recent research source on surgical robotics data access barriers and multimodal dataset creation.",
    "accessedOn": "2026-05-25"
  }
]
