[
  {
    "id": "metlife-2024-10k",
    "title": "MetLife 2024 Annual Report on Form 10-K",
    "url": "https://www.sec.gov/Archives/edgar/data/1099219/000109921925000044/met-20241231.htm",
    "kind": "regulatory-filing",
    "publisher": "U.S. Securities and Exchange Commission",
    "note": "Primary filing for MetLife business description, segment context, and 2024 financial performance.",
    "accessedOn": "2026-06-01"
  },
  {
    "id": "metlife-insurance-products",
    "title": "Insurance and Employee Benefits",
    "url": "https://www.metlife.com/insurance/",
    "kind": "product-page",
    "publisher": "MetLife",
    "note": "Company product page describing consumer and workplace insurance and benefit categories.",
    "accessedOn": "2026-06-01"
  },
  {
    "id": "metlife-employee-benefits",
    "title": "Employee Benefits",
    "url": "https://www.metlife.com/business-and-brokers/employee-benefits/",
    "kind": "product-page",
    "publisher": "MetLife",
    "note": "MetLife page describing employer benefit offerings including accident and health, dental, disability, life, and legal services.",
    "accessedOn": "2026-06-01"
  },
  {
    "id": "metlife-life-products",
    "title": "Individual Life Insurance Policy Types",
    "url": "https://www.metlife.com/support-and-manage/current-customers/individual-life-insurance/products/",
    "kind": "product-page",
    "publisher": "MetLife",
    "note": "MetLife support page identifying term, whole, universal, and variable universal life insurance policy types.",
    "accessedOn": "2026-06-01"
  },
  {
    "id": "stockanalysis-met-market-cap",
    "title": "MetLife Market Cap",
    "url": "https://stockanalysis.com/stocks/met/market-cap/",
    "kind": "market-data",
    "publisher": "StockAnalysis",
    "note": "Market-data reference for current MetLife market capitalization.",
    "accessedOn": "2026-06-01"
  },
  {
    "id": "stockanalysis-met-statistics",
    "title": "MetLife Statistics and Valuation",
    "url": "https://stockanalysis.com/stocks/met/statistics/",
    "kind": "market-data",
    "publisher": "StockAnalysis",
    "note": "Market-data reference for valuation and market capitalization context.",
    "accessedOn": "2026-06-01"
  },
  {
    "id": "openimis-home",
    "title": "openIMIS Home Page",
    "url": "https://www.openimis.org/",
    "kind": "open-source-project",
    "publisher": "openIMIS Initiative",
    "note": "Open-source digital public-good platform for health financing and social protection administration.",
    "accessedOn": "2026-06-01"
  },
  {
    "id": "openimis-what",
    "title": "What is openIMIS?",
    "url": "https://openimis.org/what-openimis",
    "kind": "technical-docs",
    "publisher": "openIMIS Initiative",
    "note": "Explains openIMIS use cases, implementation scope, and beneficiary scale.",
    "accessedOn": "2026-06-01"
  },
  {
    "id": "openimis-github",
    "title": "openIMIS GitHub Organization",
    "url": "https://github.com/openimis",
    "kind": "open-source-project",
    "publisher": "GitHub",
    "note": "Public repositories for the openIMIS open-source software ecosystem.",
    "accessedOn": "2026-06-01"
  },
  {
    "id": "nexus-mutual-docs",
    "title": "The Nexus Mutual Protocol",
    "url": "https://docs.nexusmutual.io/protocol/",
    "kind": "technical-docs",
    "publisher": "Nexus Mutual",
    "note": "Documentation for a decentralized insurance alternative based on member risk sharing.",
    "accessedOn": "2026-06-01"
  },
  {
    "id": "nexus-mutual-faq",
    "title": "Nexus Mutual FAQ",
    "url": "https://nexusmutual.io/faq",
    "kind": "technical-docs",
    "publisher": "Nexus Mutual",
    "note": "FAQ context for Nexus Mutual cover products and claims process.",
    "accessedOn": "2026-06-01"
  },
  {
    "id": "soa-decentralized-insurance",
    "title": "Decentralized Insurance",
    "url": "https://www.soa.org/4aa5c3/globalassets/assets/files/resources/research-report/2022/decentralized-ins-alt.pdf",
    "kind": "analysis",
    "publisher": "Society of Actuaries",
    "note": "Actuarial analysis of decentralized insurance models, including parametric structures and oracle needs.",
    "accessedOn": "2026-06-01"
  },
  {
    "id": "horilla-home",
    "title": "Horilla Open Source HR Software",
    "url": "https://www.horilla.com/",
    "kind": "open-source-project",
    "publisher": "Horilla",
    "note": "Open-source HRMS project relevant to the administration layer of employee benefits.",
    "accessedOn": "2026-06-01"
  },
  {
    "id": "horilla-github",
    "title": "Horilla GitHub Repository",
    "url": "https://github.com/horilla-opensource/horilla",
    "kind": "open-source-project",
    "publisher": "GitHub",
    "note": "Public source repository for Horilla HRMS.",
    "accessedOn": "2026-06-01"
  }
]
