{
  "schemaVersion": 1,
  "slug": "vici-properties",
  "name": "VICI Properties",
  "ticker": "VICI",
  "regionId": "us",
  "indexIds": [
    "sp500-top300"
  ],
  "sectorId": "real-estate",
  "industryId": "gaming-reits",
  "companiesMarketCapUrl": "https://companiesmarketcap.com/vici-properties/marketcap/",
  "description": "VICI Properties is a REIT that owns gaming, hospitality, and entertainment real estate leased to experiential operators.",
  "technologyWaveIds": [],
  "seedProductNames": [
    "Gaming real estate portfolio"
  ],
  "seedSourceUrls": [
    "https://www.viciproperties.com/",
    "https://companiesmarketcap.com/vici-properties/marketcap/"
  ],
  "notes": "Queued from the May 25, 2026 S&P 500 market-cap snapshot ranks 276-300."
}
