{
  "schemaVersion": 1,
  "slug": "western-digital",
  "name": "Western Digital",
  "ticker": "WDC",
  "regionId": "us",
  "indexIds": [
    "sp500-top75"
  ],
  "sectorId": "information-technology",
  "industryId": "technology-hardware",
  "companiesMarketCapUrl": "https://companiesmarketcap.com/western-digital/marketcap/",
  "description": "Western Digital develops and sells data storage devices and platforms, including hard drives and flash-based storage.",
  "technologyWaveIds": [],
  "seedProductNames": [
    "WD_BLACK",
    "Ultrastar"
  ],
  "seedSourceUrls": [
    "https://investor.wdc.com/",
    "https://www.westerndigital.com/products",
    "https://companiesmarketcap.com/western-digital/marketcap/"
  ],
  "notes": "Queued from the May 25, 2026 S&P 500 market-cap snapshot ranks 51-75."
}
