{
  "schemaVersion": 1,
  "slug": "microchip-technology",
  "name": "Microchip Technology",
  "ticker": "MCHP",
  "regionId": "us",
  "indexIds": [
    "sp500-top225"
  ],
  "sectorId": "information-technology",
  "industryId": "semiconductors",
  "companiesMarketCapUrl": "https://companiesmarketcap.com/microchip-technology/marketcap/",
  "description": "Microchip Technology designs, manufactures, and sells embedded-control semiconductors, including microcontrollers, mixed-signal, analog, and Flash-IP products.",
  "technologyWaveIds": [
    "printed-electronics",
    "microfactories"
  ],
  "maybeIpo": null,
  "seedProductNames": [
    "PIC microcontrollers",
    "AVR microcontrollers"
  ],
  "seedSourceUrls": [
    "https://ir.microchip.com/sec-filings/all-sec-filings/content/0000827054-26-000016/0000827054-26-000016.pdf",
    "https://www.microchip.com/en-us/products/microcontrollers/",
    "https://www.microchip.com/en-us/products/microcontrollers/8-bit-mcus",
    "https://stockanalysis.com/stocks/mchp/statistics/"
  ],
  "notes": "Queued from the May 25, 2026 S&P 500 market-cap snapshot ranks 201-225."
}
