{
  "schemaVersion": 1,
  "runId": "2026-05-27T23-13-45-118Z",
  "companySlug": "waste-management",
  "mode": "dry-run",
  "requestedProvider": "codex",
  "resolvedProviders": [
    "codex"
  ],
  "taskResults": [
    {
      "taskId": "company-sync",
      "provider": "codex",
      "promptFile": "research/runs/waste-management/2026-05-27T23-13-45-118Z/company-sync.prompt.md",
      "rawOutputFile": "research/runs/waste-management/2026-05-27T23-13-45-118Z/company-sync.codex.raw.txt",
      "normalizedFile": "research/runs/waste-management/2026-05-27T23-13-45-118Z/company-sync.codex.normalized.json",
      "validationFile": "research/runs/waste-management/2026-05-27T23-13-45-118Z/company-sync.codex.validation.json",
      "exitCode": 0,
      "success": true,
      "timedOut": false,
      "generatedOn": "2026-05-27T23:15:45.167Z"
    },
    {
      "taskId": "implementation-prompts",
      "provider": "local",
      "promptFile": "research/runs/waste-management/2026-05-27T23-13-45-118Z/implementation-prompts.prompt.md",
      "rawOutputFile": "research/runs/waste-management/2026-05-27T23-13-45-118Z/implementation-prompts.local.raw.txt",
      "normalizedFile": "research/runs/waste-management/2026-05-27T23-13-45-118Z/implementation-prompts.local.normalized.json",
      "validationFile": "research/runs/waste-management/2026-05-27T23-13-45-118Z/implementation-prompts.local.validation.json",
      "exitCode": 0,
      "success": true,
      "generatedOn": "2026-05-27T23:15:45.171Z"
    }
  ],
  "generatedOn": "2026-05-27T23:15:45.171Z",
  "publishedSourceIds": [
    "wm-2025-10k",
    "wm-residential-services",
    "wm-recycling-services",
    "macrotrends-wm-marketcap",
    "macrotrends-wm-pe",
    "stockanalysis-wm-financials",
    "epa-payt",
    "openlittermap-home",
    "openlittermap-about",
    "openlittermap-terms",
    "openlittermap-github",
    "precious-plastic-machines",
    "ereuse-open-source-platform"
  ]
}
