{
  "schemaVersion": 1,
  "slug": "booking-holdings",
  "name": "Booking Holdings",
  "ticker": "BKNG",
  "regionId": "us",
  "indexIds": [
    "sp500-top100"
  ],
  "sectorId": "consumer-discretionary",
  "industryId": "travel-services",
  "companiesMarketCapUrl": "https://companiesmarketcap.com/booking-holdings/marketcap/",
  "description": "Booking Holdings operates global online travel and restaurant reservation platforms including Booking.com, Priceline, Agoda, KAYAK, and OpenTable.",
  "technologyWaveIds": [
    "bitcoin-native-coordination"
  ],
  "maybeIpo": null,
  "seedProductNames": [
    "Booking.com",
    "Priceline"
  ],
  "seedSourceUrls": [
    "https://www.sec.gov/Archives/edgar/data/1075531/000107553126000009/bkng-20251231.htm",
    "https://ir.bookingholdings.com/financials/annual-reports/default.aspx?LanguageId=1",
    "https://www.bookingholdings.com/wp-content/uploads/2026/02/Q4-25-BKNG-Earnings-Release.pdf",
    "https://stockanalysis.com/stocks/bkng/"
  ],
  "notes": "Queued from the May 25, 2026 S&P 500 market-cap snapshot ranks 76-100."
}
