{
  "id": "wd-capacity-sold-out",
  "title": "Western Digital is already sold out of hard drives for all of 2026",
  "url": "https://www.tomshardware.com/pc-components/hdds/western-digital-is-already-sold-out-of-hard-drives-for-all-of-2026-chief-says-some-long-term-agreements-for-2027-and-2028-already-in-place",
  "kind": "analysis",
  "publisher": "Tom's Hardware",
  "note": "Reports management comments about 2026 HDD capacity being booked by large customers, useful for supply-concentration and shortage context.",
  "accessedOn": "2026-05-26"
}
